{"arch_packages": "arm_cortex-a7_neon-vfpv4", "build_at": "2021-02-17 16:55:19", "default_packages": ["base-files", "libc", "libgcc", "busybox", "dropbear", "mtd", "uci", "opkg", "netifd", "fstools", "uclient-fetch", "logd", "urandom-seed", "urngd", "kmod-usb-dwc3-of-simple", "kmod-leds-gpio", "kmod-gpio-button-hotplug", "swconfig", "kmod-ath10k-ct", "wpad-basic", "kmod-usb3", "kmod-usb-dwc3", "ath10k-firmware-qca4019-ct", "dnsmasq", "iptables", "ip6tables", "ppp", "ppp-mod-pppoe", "firewall", "odhcpd-ipv6only", "odhcp6c", "kmod-ipt-offload", "kmod-usb-dwc3-of-simple", "kmod-leds-gpio", "kmod-gpio-button-hotplug", "swconfig", "kmod-ath10k-ct", "wpad-basic", "kmod-usb3", "kmod-usb-dwc3", "ath10k-firmware-qca4019-ct"], "device_packages": ["uboot-envtools"], "id": "openmesh_a42", "image_prefix": "openwrt-19.07.7-ipq40xx-generic-openmesh_a42", "images": [{"filesystem": "squashfs", "name": "openwrt-19.07.7-ipq40xx-generic-openmesh_a42-squashfs-sysupgrade.bin", "sha256": "f605202d41fdfaac609a930008058d684f725cd25716c4534d86c9d12ebba85c", "type": "sysupgrade"}, {"filesystem": "squashfs", "name": "openwrt-19.07.7-ipq40xx-generic-openmesh_a42-squashfs-factory.bin", "sha256": "59302a998eeab2677a9c3a4bb8d5659f15fa22ffdd623d783175ed34e57fcf64", "type": "factory"}], "metadata_version": 1, "supported_devices": ["openmesh,a42"], "target": "ipq40xx/generic", "titles": [{"title": "OpenMesh A42"}], "version_code": "r11306-c4a6851c72", "version_number": "19.07.7"}