{"arch_packages": "mipsel_24kc", "build_at": "2021-02-17 13:45:19", "default_packages": ["base-files", "libc", "libgcc", "busybox", "dropbear", "mtd", "uci", "opkg", "netifd", "fstools", "uclient-fetch", "logd", "urandom-seed", "urngd", "kmod-leds-gpio", "kmod-gpio-button-hotplug", "swconfig", "kmod-mt7603", "wpad-basic", "dnsmasq", "iptables", "ip6tables", "ppp", "ppp-mod-pppoe", "firewall", "odhcpd-ipv6only", "odhcp6c", "kmod-ipt-offload", "kmod-leds-gpio", "kmod-gpio-button-hotplug", "swconfig"], "device_packages": ["kmod-usb2", "kmod-usb-ohci"], "id": "widora_neo-16m", "image_prefix": "openwrt-19.07.7-ramips-mt76x8-widora_neo-16m", "images": [{"filesystem": "squashfs", "name": "openwrt-19.07.7-ramips-mt76x8-widora_neo-16m-squashfs-sysupgrade.bin", "sha256": "ec6bf1bbab784420039ba89b64f2283e9ba030afa2f44ecc7fc87597cb7c8357", "type": "sysupgrade"}], "metadata_version": 1, "supported_devices": ["widora,neo-16m", "widora-neo"], "target": "ramips/mt76x8", "titles": [{"title": "Widora-NEO (16M)"}], "version_code": "r11306-c4a6851c72", "version_number": "19.07.7"}