{"arch_packages": "arm_xscale", "build_at": "2021-01-09 16:27:20", "default_packages": ["base-files", "ca-bundle", "dropbear", "fstools", "libc", "libgcc", "libustream-wolfssl", "logd", "mtd", "netifd", "opkg", "uci", "uclient-fetch", "urandom-seed", "urngd", "busybox", "procd", "uboot-envtools", "kmod-usb2", "dnsmasq", "firewall", "ip6tables", "iptables", "kmod-ipt-offload", "odhcp6c", "odhcpd-ipv6only", "ppp", "ppp-mod-pppoe", "uboot-envtools", "kmod-usb2"], "device_packages": ["kmod-ata-marvell-sata", "kmod-fs-ext4"], "id": "seagate_goflexnet", "image_prefix": "openwrt-kirkwood-seagate_goflexnet", "images": [{"filesystem": "squashfs", "name": "openwrt-kirkwood-seagate_goflexnet-squashfs-factory.bin", "sha256": "fa2ca840f28c7b97a1527e7f7b00ee7ad3e34d0a02aa8ccc9c8b8b44fb3cf928", "type": "factory"}, {"filesystem": "squashfs", "name": "openwrt-kirkwood-seagate_goflexnet-squashfs-sysupgrade.bin", "sha256": "452930e27c5cca095ebc7eb0f0a7431a8ef31bf7c38f6d1ff720312a9fea6c61", "type": "sysupgrade"}], "metadata_version": 1, "source_date_epoch": "1610184244", "supported_devices": ["seagate,goflexnet", "goflexnet"], "target": "kirkwood/generic", "titles": [{"model": "GoFlexNet", "vendor": "Seagate"}], "version_code": "r15466-2e590a6364", "version_number": "SNAPSHOT"}