{"arch_packages": "mips_24kc", "build_at": "2021-02-17 11:47:07", "default_packages": ["base-files", "libc", "libgcc", "busybox", "dropbear", "mtd", "uci", "opkg", "netifd", "fstools", "uclient-fetch", "logd", "urandom-seed", "urngd", "kmod-gpio-button-hotplug", "swconfig", "kmod-ath9k", "uboot-envtools", "wpad-basic", "dnsmasq", "iptables", "ip6tables", "ppp", "ppp-mod-pppoe", "firewall", "odhcpd-ipv6only", "odhcp6c", "kmod-ipt-offload", "kmod-gpio-button-hotplug", "swconfig", "kmod-ath9k", "uboot-envtools"], "device_packages": ["kmod-usb-core", "kmod-usb2", "kmod-usb-storage", "kmod-i2c-core", "kmod-i2c-gpio-custom", "kmod-spi-bitbang", "kmod-spi-dev", "kmod-spi-gpio", "kmod-spi-gpio-custom", "kmod-usb-serial"], "id": "onion-omega", "image_prefix": "openwrt-19.07.7-ar71xx-generic-onion-omega", "images": [{"filesystem": "squashfs", "name": "openwrt-19.07.7-ar71xx-generic-onion-omega-squashfs-sysupgrade.bin", "sha256": "087fc75a667d05cbc5cb94dcfbf16c47c63d2d191f355641296683579d90753e", "type": "sysupgrade"}, {"filesystem": "squashfs", "name": "openwrt-19.07.7-ar71xx-generic-onion-omega-squashfs-factory.bin", "sha256": "fc54366656f06800bcda6cf79d3a374d367fd4b5fdc0a5c392545ea8b5a3a5a5", "type": "factory"}], "metadata_version": 1, "supported_devices": [], "target": "ar71xx/generic", "titles": [{"title": "Onion Omega"}], "version_code": "r11306-c4a6851c72", "version_number": "19.07.7"}