{"arch_packages": "mips_24kc", "build_at": "2021-02-17 11:47:07", "default_packages": ["base-files", "libc", "libgcc", "busybox", "dropbear", "mtd", "uci", "opkg", "netifd", "fstools", "uclient-fetch", "logd", "urandom-seed", "urngd", "kmod-gpio-button-hotplug", "swconfig", "kmod-ath9k", "uboot-envtools", "wpad-basic", "dnsmasq", "iptables", "ip6tables", "ppp", "ppp-mod-pppoe", "firewall", "odhcpd-ipv6only", "odhcp6c", "kmod-ipt-offload", "kmod-gpio-button-hotplug", "swconfig", "kmod-ath9k", "uboot-envtools"], "device_packages": ["kmod-usb-core", "kmod-usb2"], "id": "tl-wr810n-v1", "image_prefix": "openwrt-19.07.7-ar71xx-generic-tl-wr810n-v1", "images": [{"filesystem": "squashfs", "name": "openwrt-19.07.7-ar71xx-generic-tl-wr810n-v1-squashfs-factory.bin", "sha256": "e9868a452c98dcff72b3376a04db2422bba3e799e8c415625a0ac4d2d55a64c4", "type": "factory"}, {"filesystem": "squashfs", "name": "openwrt-19.07.7-ar71xx-generic-tl-wr810n-v1-squashfs-sysupgrade.bin", "sha256": "2c0610a22b21273d766d35523e875bc27b58d9136ebccf6f2142bd94b5c42559", "type": "sysupgrade"}], "metadata_version": 1, "supported_devices": [], "target": "ar71xx/generic", "titles": [{"title": "TP-LINK TL-WR810N v1"}], "version_code": "r11306-c4a6851c72", "version_number": "19.07.7"}