{"arch_packages": "arm_cortex-a9_neon", "build_at": "2021-04-20 19:23:49", "default_packages": ["base-files", "busybox", "ca-bundle", "dnsmasq", "dropbear", "e2fsprogs", "firewall", "fstools", "ip6tables", "iptables", "kmod-fs-msdos", "kmod-ipt-offload", "kmod-usb-storage", "libc", "libgcc", "libustream-wolfssl", "logd", "mkf2fs", "mtd", "netifd", "odhcp6c", "odhcpd-ipv6only", "opkg", "ppp", "ppp-mod-pppoe", "procd", "uboot-envtools", "uci", "uclient-fetch", "urandom-seed", "urngd"], "device_packages": ["kmod-can", "kmod-can-xilinx-can"], "id": "xlnx_zynq-zc702", "image_prefix": "openwrt-21.02.0-rc1-zynq-xlnx_zynq-zc702", "images": [{"filesystem": "squashfs", "name": "openwrt-21.02.0-rc1-zynq-xlnx_zynq-zc702-squashfs-sdcard.img.gz", "sha256": "8492e16742c42b2e63549e5b79fb588b4a0edc03bdfe4e2e5e8705c4e12f45bc", "type": "sdcard"}], "metadata_version": 1, "source_date_epoch": "1618740417", "supported_devices": ["xlnx,zynq-zc702"], "target": "zynq/generic", "titles": [{"model": "ZC702", "vendor": "Xilinx"}], "version_code": "r16046-59980f7aaf", "version_number": "21.02.0-rc1"}