{"arch_packages": "arm_cortex-a9_vfpv3-d16", "build_at": "2021-04-21 10:23:00", "default_packages": ["base-files", "busybox", "ca-bundle", "dnsmasq", "dropbear", "firewall", "fstools", "ip6tables", "iptables", "kmod-gpio-button-hotplug", "kmod-ipt-offload", "libc", "libgcc", "libustream-wolfssl", "logd", "mtd", "netifd", "odhcp6c", "odhcpd-ipv6only", "opkg", "ppp", "ppp-mod-pppoe", "procd", "uboot-envtools", "uci", "uclient-fetch", "urandom-seed", "urngd"], "device_packages": ["mkf2fs", "e2fsprogs", "partx-utils"], "id": "kobol_helios4", "image_prefix": "openwrt-21.02.0-rc1-mvebu-cortexa9-kobol_helios4", "images": [{"filesystem": "squashfs", "name": "openwrt-21.02.0-rc1-mvebu-cortexa9-kobol_helios4-squashfs-sdcard.img.gz", "sha256": "c4f864049cb967f82594c537deac9b187b02415faa9e803c7118d6b13d27618c", "type": "sdcard"}], "metadata_version": 1, "source_date_epoch": "1618740417", "supported_devices": ["kobol,helios4"], "target": "mvebu/cortexa9", "titles": [{"model": "Helios4", "vendor": "Kobol"}], "version_code": "r16046-59980f7aaf", "version_number": "21.02.0-rc1"}