{"arch_packages": "arm_cortex-a9_vfpv3-d16", "build_at": "2021-04-21 10:23:00", "default_packages": ["base-files", "busybox", "ca-bundle", "dnsmasq", "dropbear", "firewall", "fstools", "ip6tables", "iptables", "kmod-gpio-button-hotplug", "kmod-ipt-offload", "libc", "libgcc", "libustream-wolfssl", "logd", "mtd", "netifd", "odhcp6c", "odhcpd-ipv6only", "opkg", "ppp", "ppp-mod-pppoe", "procd", "uboot-envtools", "uci", "uclient-fetch", "urandom-seed", "urngd"], "device_packages": ["kmod-mwlwifi", "wpad-basic-wolfssl", "kmod-btmrvl", "kmod-mwifiex-sdio", "mwlwifi-firmware-88w8964", "iwinfo"], "id": "linksys_wrt32x", "image_prefix": "openwrt-21.02.0-rc1-mvebu-cortexa9-linksys_wrt32x", "images": [{"filesystem": "squashfs", "name": "openwrt-21.02.0-rc1-mvebu-cortexa9-linksys_wrt32x-squashfs-factory.img", "sha256": "6150530bbde726050952b6da9bd9d3ec4a1d8150bc78d50b73e17e23345dc382", "type": "factory"}, {"filesystem": "squashfs", "name": "openwrt-21.02.0-rc1-mvebu-cortexa9-linksys_wrt32x-squashfs-sysupgrade.bin", "sha256": "e5684bea1396aebdb4bb602f4b37c4a2322f4b46ee528fc52cd92bcc427430af", "type": "sysupgrade"}], "metadata_version": 1, "source_date_epoch": "1618740417", "supported_devices": ["linksys,wrt32x", "armada-385-linksys-venom", "linksys,venom"], "target": "mvebu/cortexa9", "titles": [{"model": "WRT32X", "vendor": "Linksys"}, {"model": "Venom", "vendor": "Linksys"}], "version_code": "r16046-59980f7aaf", "version_number": "21.02.0-rc1"}