{"arch_packages": "mipsel_24kc", "build_at": "2021-05-02 15:20:25", "default_packages": ["base-files", "busybox", "ca-bundle", "dnsmasq", "dropbear", "firewall", "fstools", "ip6tables", "iptables", "kmod-gpio-button-hotplug", "kmod-ipt-offload", "kmod-leds-gpio", "kmod-rt2800-soc", "libc", "libgcc", "libustream-wolfssl", "logd", "mtd", "netifd", "odhcp6c", "odhcpd-ipv6only", "opkg", "ppp", "ppp-mod-pppoe", "procd", "swconfig", "uci", "uclient-fetch", "urandom-seed", "urngd", "wpad-basic-wolfssl"], "device_packages": ["kmod-usb2", "kmod-usb-ohci", "kmod-usb-ledtrig-usbport", "kmod-switch-rtl8366-smi", "kmod-switch-rtl8367b"], "id": "kimax_u25awf-h1", "image_prefix": "openwrt-ramips-mt7620-kimax_u25awf-h1", "images": [{"filesystem": "initramfs", "name": "openwrt-ramips-mt7620-kimax_u25awf-h1-initramfs-kernel.bin", "sha256": "d8f3b9da89d35246b18f6c9962be32d71259399c9cf3f0e9a9ab10753745576f", "type": "kernel"}, {"filesystem": "squashfs", "name": "openwrt-ramips-mt7620-kimax_u25awf-h1-squashfs-sysupgrade.bin", "sha256": "e78d4a0465dc36d52e5d368cd0527520c85c36d8f7d3e27f771be9497261b44d", "type": "sysupgrade"}], "metadata_version": 1, "source_date_epoch": "1619916020", "supported_devices": ["kimax,u25awf-h1", "u25awf-h1"], "target": "ramips/mt7620", "titles": [{"model": "U25AWF", "variant": "H1", "vendor": "Kimax"}], "version_code": "r16633-5515c29029", "version_number": "SNAPSHOT"}