{"arch_packages": "mipsel_24kc", "build_at": "2021-04-21 02:54:19", "default_packages": ["base-files", "busybox", "ca-bundle", "dnsmasq", "dropbear", "firewall", "fstools", "ip6tables", "iptables", "kmod-gpio-button-hotplug", "kmod-ipt-offload", "kmod-leds-gpio", "kmod-rt2800-soc", "libc", "libgcc", "libustream-wolfssl", "logd", "mtd", "netifd", "odhcp6c", "odhcpd-ipv6only", "opkg", "ppp", "ppp-mod-pppoe", "procd", "swconfig", "uci", "uclient-fetch", "urandom-seed", "urngd", "wpad-basic-wolfssl"], "device_packages": ["kmod-usb2", "kmod-usb-ohci", "kmod-i2c-ralink"], "id": "hootoo_ht-tm05", "image_prefix": "openwrt-21.02.0-rc1-ramips-mt7620-hootoo_ht-tm05", "images": [{"filesystem": "squashfs", "name": "openwrt-21.02.0-rc1-ramips-mt7620-hootoo_ht-tm05-squashfs-kernel.bin", "sha256": "676db6c10d599f4cc29e810c4723d0dbe9991389e7acbba8ec4810d94d2768f3", "type": "kernel"}, {"filesystem": "squashfs", "name": "openwrt-21.02.0-rc1-ramips-mt7620-hootoo_ht-tm05-squashfs-rootfs.bin", "sha256": "7b6308f9f649fc275ffc4c25b1bb928f2c688e0bc0386f738f70d136e40e9813", "type": "rootfs"}, {"filesystem": "squashfs", "name": "openwrt-21.02.0-rc1-ramips-mt7620-hootoo_ht-tm05-squashfs-sysupgrade.bin", "sha256": "7d4024bb72e834f84760f57b986bc781d7b9e2c5b57559e29af3182ed5603abd", "type": "sysupgrade"}], "metadata_version": 1, "source_date_epoch": "1618740417", "supported_devices": ["hootoo,ht-tm05"], "target": "ramips/mt7620", "titles": [{"model": "HT-TM05", "vendor": "HooToo"}], "version_code": "r16046-59980f7aaf", "version_number": "21.02.0-rc1"}