{"arch_packages": "arm_cortex-a7_neon-vfpv4", "build_at": "2021-03-20 08:24:58", "default_packages": ["base-files", "ca-bundle", "dropbear", "fstools", "libc", "libgcc", "libustream-wolfssl", "logd", "mtd", "netifd", "opkg", "uci", "uclient-fetch", "urandom-seed", "urngd", "busybox", "procd", "kmod-usb-dwc3-qcom", "kmod-leds-gpio", "kmod-gpio-button-hotplug", "swconfig", "kmod-ath10k-ct", "wpad-basic-wolfssl", "kmod-usb3", "kmod-usb-dwc3", "ath10k-firmware-qca4019-ct", "dnsmasq", "firewall", "ip6tables", "iptables", "kmod-ipt-offload", "odhcp6c", "odhcpd-ipv6only", "ppp", "ppp-mod-pppoe", "kmod-usb-dwc3-qcom", "kmod-leds-gpio", "kmod-gpio-button-hotplug", "swconfig", "kmod-ath10k-ct", "wpad-basic-wolfssl", "kmod-usb3", "kmod-usb-dwc3", "ath10k-firmware-qca4019-ct"], "device_packages": ["-kmod-ath10k-ct", "kmod-ath10k-ct-smallbuffers"], "id": "dlink_dap-2610", "image_prefix": "openwrt-ipq40xx-generic-zyxel_wre6606", "images": [{"filesystem": "initramfs", "name": "openwrt-ipq40xx-generic-dlink_dap-2610-initramfs-fit-uImage.itb", "sha256": "b95cd8f95a3ebe3b6dc291a1d613714fee2a59f87224b23c513f539c26559162", "type": "kernel"}, {"filesystem": "squashfs", "name": "openwrt-ipq40xx-generic-dlink_dap-2610-squashfs-factory.bin", "sha256": "646fb81fa0f782ddaf181aee237711a48b06136e14dc34a8943137912798e710", "type": "factory"}, {"filesystem": "squashfs", "name": "openwrt-ipq40xx-generic-dlink_dap-2610-squashfs-sysupgrade.bin", "sha256": "dd64ab7317c22647fb253304c11cc5d9912d9fb4f2928bfea743f58977114b2b", "type": "sysupgrade"}], "metadata_version": 1, "source_date_epoch": "1616197071", "supported_devices": ["dlink,dap-2610"], "target": "ipq40xx/generic", "titles": [{"model": "DAP-2610", "vendor": "D-Link"}], "version_code": "r16287-7fae64cc06", "version_number": "SNAPSHOT"}