{"arch_packages": "arm_cortex-a9", "build_at": "2021-03-20 17:26:43", "default_packages": ["base-files", "ca-bundle", "dropbear", "fstools", "libc", "libgcc", "libustream-wolfssl", "logd", "mtd", "netifd", "opkg", "uci", "uclient-fetch", "urandom-seed", "urngd", "busybox", "procd", "swconfig", "nvram", "osafeloader", "oseama", "otrx", "kmod-gpio-button-hotplug", "kmod-leds-gpio", "dnsmasq", "firewall", "ip6tables", "iptables", "kmod-ipt-offload", "odhcp6c", "odhcpd-ipv6only", "ppp", "ppp-mod-pppoe", "swconfig", "nvram", "osafeloader", "oseama", "otrx", "kmod-gpio-button-hotplug", "kmod-leds-gpio"], "device_packages": ["wpad-basic-wolfssl", "kmod-b43", "kmod-usb-ohci", "kmod-usb2", "kmod-phy-bcm-ns-usb2", "kmod-usb-ledtrig-usbport", "kmod-usb3", "kmod-phy-bcm-ns-usb3", "iwinfo"], "id": "netgear_r6300-v2", "image_prefix": "openwrt-bcm53xx-generic-netgear_r6300-v2", "images": [{"filesystem": "squashfs", "name": "openwrt-bcm53xx-generic-netgear_r6300-v2-squashfs.chk", "sha256": "72dcd747db1f943dd330f23eff1b7f3709d4a06e0cda365c358d8f7005b53a0e", "type": "chk"}], "metadata_version": 1, "source_date_epoch": "1616197071", "supported_devices": ["netgear,r6300-v2"], "target": "bcm53xx/generic", "titles": [{"model": "R6300", "variant": "v2", "vendor": "NETGEAR"}], "version_code": "r16287-7fae64cc06", "version_number": "SNAPSHOT"}