{"arch_packages": "mips_24kc", "build_at": "2021-02-17 19:22:01", "default_packages": ["base-files", "libc", "libgcc", "busybox", "dropbear", "mtd", "uci", "opkg", "netifd", "fstools", "uclient-fetch", "logd", "urandom-seed", "urngd", "kmod-gpio-button-hotplug", "swconfig", "kmod-ath9k", "uboot-envtools", "wpad-basic", "dnsmasq", "iptables", "ip6tables", "ppp", "ppp-mod-pppoe", "firewall", "odhcpd-ipv6only", "odhcp6c", "kmod-ipt-offload", "kmod-gpio-button-hotplug", "swconfig", "kmod-ath9k", "uboot-envtools"], "device_packages": [], "id": "xiaomi_mi-router-4q", "image_prefix": "openwrt-19.07.7-ath79-generic-xiaomi_mi-router-4q", "images": [{"filesystem": "squashfs", "name": "openwrt-19.07.7-ath79-generic-xiaomi_mi-router-4q-squashfs-sysupgrade.bin", "sha256": "90ba79a8dcc7e47449cc3b6bbe035d3079e063af3782f7ebdec96f80f8afbec4", "type": "sysupgrade"}], "metadata_version": 1, "supported_devices": ["xiaomi,mi-router-4q"], "target": "ath79/generic", "titles": [{"title": "Xiaomi Mi Router 4Q"}], "version_code": "r11306-c4a6851c72", "version_number": "19.07.7"}