{"arch_packages": "arm_arm926ej-s", "build_at": "2021-03-20 06:59:11", "default_packages": ["base-files", "ca-bundle", "dropbear", "fstools", "libc", "libgcc", "libustream-wolfssl", "logd", "mtd", "netifd", "opkg", "uci", "uclient-fetch", "urandom-seed", "urngd", "busybox", "procd", "kmod-usb-ohci", "kmod-at91-udc", "kmod-usb-gadget-eth", "dnsmasq", "firewall", "ip6tables", "iptables", "kmod-ipt-offload", "odhcp6c", "odhcpd-ipv6only", "ppp", "ppp-mod-pppoe", "kmod-usb-ohci", "kmod-at91-udc", "kmod-usb-gadget-eth"], "device_packages": [], "id": "calao_usb-a9g20", "image_prefix": "openwrt-at91-sam9x-calao_usb-a9g20", "images": [{"filesystem": "ubifs", "name": "openwrt-at91-sam9x-calao_usb-a9g20-ubifs-factory.bin", "sha256": "dcc2ca9b7957eb5616913e0d32f300f79c825dd39571d7424421084de6b461ba", "type": "factory"}, {"filesystem": "squashfs", "name": "openwrt-at91-sam9x-calao_usb-a9g20-squashfs-factory.bin", "sha256": "0b1238017c9ace4ac86eae3ac5b843f7b6294f8c5483a096bd150bea124b51e6", "type": "factory"}], "metadata_version": 1, "source_date_epoch": "1616197071", "supported_devices": ["calao,usb-a9g20"], "target": "at91/sam9x", "titles": [{"model": "USB A9G20", "vendor": "Calao"}], "version_code": "r16287-7fae64cc06", "version_number": "SNAPSHOT"}