{"arch_packages": "mipsel_24kc", "build_at": "2021-01-10 02:47:37", "default_packages": ["base-files", "ca-bundle", "dropbear", "fstools", "libc", "libgcc", "libustream-wolfssl", "logd", "mtd", "netifd", "opkg", "uci", "uclient-fetch", "urandom-seed", "urngd", "busybox", "procd", "kmod-leds-gpio", "kmod-gpio-button-hotplug", "kmod-mt7603", "wpad-basic-wolfssl", "swconfig", "dnsmasq", "firewall", "ip6tables", "iptables", "kmod-ipt-offload", "odhcp6c", "odhcpd-ipv6only", "ppp", "ppp-mod-pppoe", "kmod-leds-gpio", "kmod-gpio-button-hotplug"], "device_packages": [], "id": "asus_rt-n12-vp-b1", "image_prefix": "openwrt-ramips-mt76x8-asus_rt-n12-vp-b1", "images": [{"filesystem": "squashfs", "name": "openwrt-ramips-mt76x8-asus_rt-n12-vp-b1-squashfs-sysupgrade.bin", "sha256": "29027f1e6d158fa796a0d8674bcb99d943709b747f7adca7f50117da21d56a21", "type": "sysupgrade"}], "metadata_version": 1, "source_date_epoch": "1610184244", "supported_devices": ["asus,rt-n12-vp-b1"], "target": "ramips/mt76x8", "titles": [{"model": "RT-N12 VP", "variant": "B1", "vendor": "Asus"}], "version_code": "r15466-2e590a6364", "version_number": "SNAPSHOT"}