{"arch_packages": "mips_24kc", "build_at": "2021-05-02 10:12:32", "default_packages": ["base-files", "busybox", "ca-bundle", "dnsmasq", "dropbear", "firewall", "fstools", "ip6tables", "iptables", "kmod-ath9k", "kmod-gpio-button-hotplug", "kmod-ipt-offload", "libc", "libgcc", "libustream-wolfssl", "logd", "mtd", "netifd", "odhcp6c", "odhcpd-ipv6only", "opkg", "ppp", "ppp-mod-pppoe", "procd", "swconfig", "uboot-envtools", "uci", "uclient-fetch", "urandom-seed", "urngd", "wpad-basic-wolfssl"], "device_packages": ["kmod-usb2", "kmod-ath10k-ct", "ath10k-firmware-qca9888-ct"], "id": "comfast_cf-e560ac", "image_prefix": "openwrt-ath79-generic-comfast_cf-e560ac", "images": [{"filesystem": "squashfs", "name": "openwrt-ath79-generic-comfast_cf-e560ac-squashfs-sysupgrade.bin", "sha256": "20acd89551ee72fa4cb542e860b96c623950dad5c1e2417546b5ee60f541536c", "type": "sysupgrade"}, {"filesystem": "initramfs", "name": "openwrt-ath79-generic-comfast_cf-e560ac-initramfs-kernel.bin", "sha256": "2b6502ec9de1e3837773c4a9b16d8e0ac0a1412d47e71d9844fe6978aee616bd", "type": "kernel"}], "metadata_version": 1, "source_date_epoch": "1619916020", "supported_devices": ["comfast,cf-e560ac"], "target": "ath79/generic", "titles": [{"model": "CF-E560AC", "vendor": "COMFAST"}], "version_code": "r16633-5515c29029", "version_number": "SNAPSHOT"}