{"arch_packages": "mips_24kc", "build_at": "2021-01-09 22:15:48", "default_packages": ["base-files", "ca-bundle", "dropbear", "fstools", "libc", "libgcc", "libustream-wolfssl", "logd", "mtd", "netifd", "opkg", "uci", "uclient-fetch", "urandom-seed", "urngd", "busybox", "procd", "kmod-gpio-button-hotplug", "swconfig", "kmod-ath9k", "uboot-envtools", "wpad-basic-wolfssl", "dnsmasq", "firewall", "ip6tables", "iptables", "kmod-ipt-offload", "odhcp6c", "odhcpd-ipv6only", "ppp", "ppp-mod-pppoe", "kmod-gpio-button-hotplug", "swconfig", "kmod-ath9k", "uboot-envtools"], "device_packages": ["kmod-usb2", "kmod-ath10k-ct", "ath10k-firmware-qca988x-ct"], "id": "iodata_wn-ac1600dgr", "image_prefix": "openwrt-ath79-generic-iodata_wn-ac1600dgr", "images": [{"filesystem": "squashfs", "name": "openwrt-ath79-generic-iodata_wn-ac1600dgr-squashfs-factory.bin", "sha256": "5ae50699cc83e0bd43c87e47c1d6d09508978a4a4503aa38a29d19746ce134cd", "type": "factory"}, {"filesystem": "squashfs", "name": "openwrt-ath79-generic-iodata_wn-ac1600dgr-squashfs-sysupgrade.bin", "sha256": "e9d8cca1ae1d9e18da381720070000ee120c48271673cf07c6a0b7562b50b3ba", "type": "sysupgrade"}], "metadata_version": 1, "source_date_epoch": "1610184244", "supported_devices": ["iodata,wn-ac1600dgr"], "target": "ath79/generic", "titles": [{"model": "WN-AC1600DGR", "vendor": "I-O DATA"}], "version_code": "r15466-2e590a6364", "version_number": "SNAPSHOT"}