{"arch_packages": "mips_24kc", "build_at": "2021-05-02 10:12:32", "default_packages": ["base-files", "busybox", "ca-bundle", "dnsmasq", "dropbear", "firewall", "fstools", "ip6tables", "iptables", "kmod-ath9k", "kmod-gpio-button-hotplug", "kmod-ipt-offload", "libc", "libgcc", "libustream-wolfssl", "logd", "mtd", "netifd", "odhcp6c", "odhcpd-ipv6only", "opkg", "ppp", "ppp-mod-pppoe", "procd", "swconfig", "uboot-envtools", "uci", "uclient-fetch", "urandom-seed", "urngd", "wpad-basic-wolfssl"], "device_packages": ["kmod-usb2"], "id": "librerouter_librerouter-v1", "image_prefix": "openwrt-ath79-generic-librerouter_librerouter-v1", "images": [{"filesystem": "squashfs", "name": "openwrt-ath79-generic-librerouter_librerouter-v1-squashfs-sysupgrade.bin", "sha256": "847ad7d282d7623736b20353adbee2ec2d4839221af4bec32a5fe1b27bc393ab", "type": "sysupgrade"}, {"filesystem": "initramfs", "name": "openwrt-ath79-generic-librerouter_librerouter-v1-initramfs-kernel.bin", "sha256": "820683e59e9d52818ba57439130226253d0bce8e9a2090c16ce556c0a7288995", "type": "kernel"}], "metadata_version": 1, "source_date_epoch": "1619916020", "supported_devices": ["librerouter,librerouter-v1"], "target": "ath79/generic", "titles": [{"model": "LibreRouter", "variant": "v1", "vendor": "Librerouter"}], "version_code": "r16633-5515c29029", "version_number": "SNAPSHOT"}