{"arch_packages": "arm_cortex-a15_neon-vfpv4", "build_at": "2021-05-02 06:08:48", "default_packages": ["base-files", "busybox", "ca-bundle", "dnsmasq", "dropbear", "firewall", "fstools", "ip6tables", "iptables", "kmod-ata-ahci", "kmod-ata-ahci-platform", "kmod-ath10k-ct", "kmod-gpio-button-hotplug", "kmod-ipt-offload", "kmod-leds-gpio", "kmod-phy-qcom-ipq806x-usb", "kmod-usb-dwc3-qcom", "kmod-usb-ledtrig-usbport", "kmod-usb-ohci", "kmod-usb2", "kmod-usb3", "libc", "libgcc", "libustream-wolfssl", "logd", "mtd", "netifd", "odhcp6c", "odhcpd-ipv6only", "opkg", "ppp", "ppp-mod-pppoe", "procd", "swconfig", "uboot-envtools", "uci", "uclient-fetch", "urandom-seed", "urngd", "wpad-basic-wolfssl"], "device_packages": ["ath10k-firmware-qca9984-ct", "e2fsprogs", "kmod-fs-ext4", "losetup"], "id": "compex_wpq864", "image_prefix": "openwrt-ipq806x-generic-compex_wpq864", "images": [{"filesystem": "initramfs", "name": "openwrt-ipq806x-generic-compex_wpq864-initramfs-fit-uImage.itb", "sha256": "2898678c0eeb981f383c264a194660a5b998b3df32254eac95a78141de45a6c6", "type": "kernel"}, {"filesystem": "squashfs", "name": "openwrt-ipq806x-generic-compex_wpq864-squashfs-nand-factory.bin", "sha256": "fe26a269bf6cf79e18ac7c3b3c1fce101cc0973983af1d60b5b211c9d3e2c7a0", "type": "nand-factory"}, {"filesystem": "squashfs", "name": "openwrt-ipq806x-generic-compex_wpq864-squashfs-nand-sysupgrade.bin", "sha256": "928af4dfd923679fdd6d31035e482e85a60769e23b4dcf10044d1c03a79d1869", "type": "nand-sysupgrade"}], "metadata_version": 1, "source_date_epoch": "1619906122", "supported_devices": ["compex,wpq864"], "target": "ipq806x/generic", "titles": [{"model": "WPQ864", "vendor": "Compex"}], "version_code": "r16632-fbcfa895a8", "version_number": "SNAPSHOT"}