{"arch_packages": "mipsel_24kc", "build_at": "2021-05-02 08:31:32", "default_packages": ["base-files", "busybox", "ca-bundle", "dnsmasq", "dropbear", "firewall", "fstools", "ip6tables", "iptables", "kmod-gpio-button-hotplug", "kmod-ipt-offload", "kmod-leds-gpio", "libc", "libgcc", "libustream-wolfssl", "logd", "mtd", "netifd", "odhcp6c", "odhcpd-ipv6only", "opkg", "ppp", "ppp-mod-pppoe", "procd", "uci", "uclient-fetch", "urandom-seed", "urngd", "wpad-basic-wolfssl"], "device_packages": ["kmod-mt7603", "kmod-mt7615e", "kmod-mt7615-firmware"], "id": "winstars_ws-wn583a6", "image_prefix": "openwrt-ramips-mt7621-winstars_ws-wn583a6", "images": [{"filesystem": "squashfs", "name": "openwrt-ramips-mt7621-winstars_ws-wn583a6-squashfs-sysupgrade.bin", "sha256": "b9a9fa2c231b78030600511668e548da129da892b31ae9afb26992946a3fe77f", "type": "sysupgrade"}, {"filesystem": "initramfs", "name": "openwrt-ramips-mt7621-winstars_ws-wn583a6-initramfs-WN583A6-kernel.bin", "sha256": "18e268dfdfc24b5b492465f89ebacc806859305947930b6ab2ed93c27d01145a", "type": "kernel"}], "metadata_version": 1, "source_date_epoch": "1619916020", "supported_devices": ["winstars,ws-wn583a6"], "target": "ramips/mt7621", "titles": [{"model": "WS-WN583A6", "vendor": "Winstars"}, {"model": "AC2100", "vendor": "Gemeita"}], "version_code": "r16633-5515c29029", "version_number": "SNAPSHOT"}