{"arch_packages": "mips_mips32", "build_at": "2021-03-20 06:26:52", "default_packages": ["base-files", "ca-bundle", "dropbear", "fstools", "libc", "libgcc", "libustream-wolfssl", "logd", "mtd", "netifd", "opkg", "uci", "uclient-fetch", "urandom-seed", "urngd", "busybox", "procd", "swconfig", "kmod-gpio-button-hotplug", "dnsmasq", "firewall", "ip6tables", "iptables", "kmod-ipt-offload", "odhcp6c", "odhcpd-ipv6only", "ppp", "ppp-mod-pppoe", "swconfig", "kmod-gpio-button-hotplug"], "device_packages": ["kmod-usb2", "kmod-usb-ohci", "kmod-usb-ledtrig-usbport", "kmod-b43", "wpad-basic-wolfssl", "iwinfo"], "id": "technicolor_tg582n", "image_prefix": "openwrt-bcm63xx-smp-technicolor_tg582n", "images": [{"filesystem": "squashfs", "name": "openwrt-bcm63xx-smp-technicolor_tg582n-squashfs-sysupgrade.bin", "sha256": "fedaa4b3401c9051335465ba679b020175c1260a6e4cc83d2262a52d16b8bf08", "type": "sysupgrade"}, {"filesystem": "squashfs", "name": "openwrt-bcm63xx-smp-technicolor_tg582n-squashfs-cfe.bin", "sha256": "c005155d1e49b6b3d055366e1a807c3c3ef3f5d33baec58cb3bbd870a3e44b4c", "type": "cfe"}], "metadata_version": 1, "source_date_epoch": "1616197071", "supported_devices": ["technicolor,tg582n"], "target": "bcm63xx/smp", "titles": [{"model": "TG582n", "vendor": "Technicolor"}], "version_code": "r16287-7fae64cc06", "version_number": "SNAPSHOT"}